lcd2usb.py
lcd2usb-1.4.dist-info/METADATA
lcd2usb-1.4.dist-info/WHEEL
lcd2usb-1.4.dist-info/top_level.txt
lcd2usb-1.4.dist-info/RECORD
