Metadata-Version: 2.1
Name: lcd2usb
Version: 1.4
Summary: LCD2USB's Python Library
Home-page: http://github.com/xyb/lib2usb
Author: Xie Yanbo
Author-email: xieyanbo@gmail.com
License: New BSD
Keywords: usb lcd lcd2usb
Platform: any
Classifier: Development Status :: 5 - Production/Stable
Classifier: Intended Audience :: Developers
Classifier: License :: OSI Approved :: BSD License
Classifier: Operating System :: OS Independent
Classifier: Programming Language :: Python
Classifier: Programming Language :: Python :: 3 :: Only
Classifier: Topic :: Software Development :: Libraries
Classifier: Topic :: System :: Hardware :: Hardware Drivers
Requires-Dist: libusb1
